<databaseChangeLog xmlns="http://www.liquibase.org/xml/ns/dbchangelog"
                   xmlns:xsi="http://www.w3.org/2001/XMLSchema-instance"
                   xsi:schemaLocation="http://www.liquibase.org/xml/ns/dbchangelog http://www.liquibase.org/xml/ns/dbchangelog/dbchangelog-3.4.xsd">

    <changeSet id="1" author="Mayank">
        <insert tableName="model">
            <column name="model_id" value="1" />
            <column name="model_name" value="may" />
            <column name="model_instaURL" value="dsadsa.com" />
            <column name="model_dpURL" value="dsadsa.com" />
            <column name="model_gender" value="male" />
            <column name="model_born" value="1198" />
            <column name="model_nationality" value="IND" />
            <column name="model_height" value="6" />
            <column name="model_figure" value="121221" />
        </insert>
    </changeSet>
</databaseChangeLog>